[
    {
        "key": "dbln",
        "value": "%7B%2261579592765139%22%3A%22uz2ME6Gr%22%7D",
        "domain": "facebook.com",
        "path": "/login/device-based/",
        "hostOnly": false,
        "creation": "2025-11-05T09:47:58.532Z",
        "lastAccessed": "2025-11-05T09:47:58.533Z"
    },
    {
        "key": "datr",
        "value": "OxwLaYqq9d2xEjbKpoVz-ccR",
        "domain": "facebook.com",
        "path": "/",
        "hostOnly": false,
        "creation": "2025-11-05T09:47:58.533Z",
        "lastAccessed": "2025-11-05T09:47:58.533Z"
    },
    {
        "key": "sb",
        "value": "OxwLaQ1qOlU4ct_Wbwkk2ieM",
        "domain": "facebook.com",
        "path": "/",
        "hostOnly": false,
        "creation": "2025-11-05T09:47:58.533Z",
        "lastAccessed": "2025-11-05T09:47:58.533Z"
    },
    {
        "key": "m_pixel_ratio",
        "value": "2",
        "domain": "facebook.com",
        "path": "/",
        "hostOnly": false,
        "creation": "2025-11-05T09:47:58.533Z",
        "lastAccessed": "2025-11-05T09:47:58.533Z"
    },
    {
        "key": "wd",
        "value": "360x800",
        "domain": "facebook.com",
        "path": "/",
        "hostOnly": false,
        "creation": "2025-11-05T09:47:58.533Z",
        "lastAccessed": "2025-11-05T09:47:58.533Z"
    },
    {
        "key": "c_user",
        "value": "61579592765139",
        "domain": "facebook.com",
        "path": "/",
        "hostOnly": false,
        "creation": "2025-11-05T09:47:58.533Z",
        "lastAccessed": "2025-11-05T09:47:58.533Z"
    },
    {
        "key": "xs",
        "value": "2%3Ah93xCogqLNQNGA%3A2%3A1762335963%3A-1%3A-1",
        "domain": "facebook.com",
        "path": "/",
        "hostOnly": false,
        "creation": "2025-11-05T09:47:58.533Z",
        "lastAccessed": "2025-11-05T09:47:58.533Z"
    },
    {
        "key": "fr",
        "value": "0OyuPvauB4D617vur.AWfhUCy4PH0er-xd7k8dA_HKnHgvRhOXdC1aIdnbFFWFZg3GCCY.BpCxw7..AAA.0.0.BpCxzk.AWfmAKdV3BMK89smZu_hBCvtCXs",
        "domain": "facebook.com",
        "path": "/",
        "hostOnly": false,
        "creation": "2025-11-05T09:47:58.533Z",
        "lastAccessed": "2025-11-05T09:47:58.533Z"
    },
    {
        "key": "locale",
        "value": "bn_IN",
        "domain": "facebook.com",
        "path": "/",
        "hostOnly": false,
        "creation": "2025-11-05T09:47:58.533Z",
        "lastAccessed": "2025-11-05T09:47:58.533Z"
    },
    {
        "key": "pas",
        "value": "61579592765139%3AZXYComkaY9",
        "domain": "facebook.com",
        "path": "/",
        "hostOnly": false,
        "creation": "2025-11-05T09:47:58.533Z",
        "lastAccessed": "2025-11-05T09:47:58.533Z"
    },
    {
        "key": "fbl_st",
        "value": "101731987%3BT%3A29372266",
        "domain": "facebook.com",
        "path": "/",
        "hostOnly": false,
        "creation": "2025-11-05T09:47:58.533Z",
        "lastAccessed": "2025-11-05T09:47:58.533Z"
    },
    {
        "key": "vpd",
        "value": "v1%3B712x360x2",
        "domain": "facebook.com",
        "path": "/",
        "hostOnly": false,
        "creation": "2025-11-05T09:47:58.533Z",
        "lastAccessed": "2025-11-05T09:47:58.533Z"
    },
    {
        "key": "wl_cbv",
        "value": "v2%3Bclient_version%3A2974%3Btimestamp%3A1762335972",
        "domain": "facebook.com",
        "path": "/",
        "hostOnly": false,
        "creation": "2025-11-05T09:47:58.533Z",
        "lastAccessed": "2025-11-05T09:47:58.533Z"
    }
]
